pactsdk/__init__.py
pactsdk/add_liquidity.py
pactsdk/api.py
pactsdk/asset.py
pactsdk/client.py
pactsdk/config.py
pactsdk/constant_product_calculator.py
pactsdk/encoding.py
pactsdk/exceptions.py
pactsdk/factories/__init__.py
pactsdk/factories/base_factory.py
pactsdk/factories/constant_product.py
pactsdk/factories/get_pool_factory.py
pactsdk/farming/README.md
pactsdk/farming/__init__.py
pactsdk/farming/escrow.py
pactsdk/farming/farm.py
pactsdk/farming/farm_state.py
pactsdk/farming/farming_client.py
pactsdk/folks_lending_pool.py
pactsdk/gas_station.py
pactsdk/pool.py
pactsdk/pool_calculator.py
pactsdk/pool_state.py
pactsdk/stableswap_calculator.py
pactsdk/swap.py
pactsdk/transaction_group.py
pactsdk/utils.py
pactsdk/zap.py
pactsdk-0.7.1.dist-info/LICENSE
pactsdk-0.7.1.dist-info/METADATA
pactsdk-0.7.1.dist-info/WHEEL
pactsdk-0.7.1.dist-info/RECORD
