Metadata-Version: 2.1
Name: pactsdk
Version: 0.7.1
Summary: Python SDK for Pact smart contracts
Home-page: https://github.com/pactfi/pact-py-sdk
License: MIT
Author: Mateusz Tomczyk
Author-email: mateusz.tomczyk@ulam.io
Requires-Python: >=3.9,<4.0
Classifier: License :: OSI Approved :: MIT License
Classifier: Programming Language :: Python :: 3
Classifier: Programming Language :: Python :: 3.9
Classifier: Programming Language :: Python :: 3.10
Classifier: Programming Language :: Python :: 3.11
Requires-Dist: cffi (>=1.15.1,<2.0.0)
Requires-Dist: py-algorand-sdk (>=2.0.0,<3.0.0)
Requires-Dist: requests (>=2.27.1,<3.0.0)
Project-URL: Repository, https://github.com/pactfi/pact-py-sdk
